[{"code":"DRW160627001","name":"Đỗ Minh Phương","al":3440,"cl":0},{"code":"APG220615003","name":"Phạm Thị Dung","al":844,"cl":0},{"code":"APG220211001","name":"Đỗ Thị Thùy Linh","al":778,"cl":0},{"code":"APG1240725003","name":"Giáp Văn Thứ","al":85,"cl":990},{"code":"APG230927001","name":"Thân Văn Huy","al":0,"cl":0},{"code":"MEM210525003","name":"Nguyễn Trường Giang","al":0,"cl":0},{"code":"API210323009","name":"Đỗ Quốc Cường","al":0,"cl":0},{"code":"API210217002","name":"Nguyễn Duy Sơn","al":432,"cl":0},{"code":"API210105007","name":"Dương Văn Hải","al":0,"cl":0},{"code":"APG230814001","name":"Dương Thị Bích Hồng","al":1156,"cl":0},{"code":"APG220725001","name":"Nguyễn Thị Huế","al":2058,"cl":0},{"code":"APG230821002","name":"Hoàng Đình Toàn","al":3030,"cl":4437},{"code":"APG230621002","name":"Đặng Thế Nam","al":2841,"cl":1212},{"code":"APG230621004","name":"Trần Văn Nhượng","al":1440,"cl":899},{"code":"APG230418001","name":"Lê Văn Hiếu","al":3637,"cl":668},{"code":"APG220801006","name":"Nguyễn Đăng Bình","al":4320,"cl":404},{"code":"APG220613004","name":"Đào Ngọc Trừu","al":5292,"cl":1094},{"code":"APG220504008","name":"Phạm Ích Linh","al":2726,"cl":1006},{"code":"APG211012014","name":"Đinh Xuân Phúc","al":1668,"cl":690},{"code":"APG210712005","name":"Chu Hoàng Long","al":609,"cl":497},{"code":"MEM210511009","name":"Đỗ Đăng Tùng","al":4673,"cl":575},{"code":"APG230321007","name":"Nguyễn Thu Hà","al":1591,"cl":0},{"code":"DRW110126001","name":"Nguyễn Quang Thuật","al":0,"cl":0},{"code":"APG240125001","name":"Vũ Thị Thoảng","al":742,"cl":0},{"code":"APG220719007","name":"Nguyễn Thị Thu Mừng","al":0,"cl":0},{"code":"APG1240701004","name":"Đào Xuân Trường","al":1920,"cl":480},{"code":"APG220707001","name":"Lê Văn Lâm","al":0,"cl":4296},{"code":"APG220216001","name":"Đặng Văn Lịu","al":960,"cl":1122},{"code":"APG211213001","name":"Lê Đình Dội","al":1440,"cl":605},{"code":"APG210624002","name":"Phạm Xuân Trưởng","al":1233,"cl":6144},{"code":"APG210817005","name":"Chu Văn Sự","al":716,"cl":0},{"code":"APG230612003","name":"Đinh Thị Ngọc Ánh","al":701,"cl":0},{"code":"APG211116011","name":"Vũ Mộng Linh","al":960,"cl":0},{"code":"APG1241213001","name":"Trịnh Thành Vinh","al":0,"cl":0},{"code":"APG230703010","name":"Nguyễn Tiến Đức","al":1920,"cl":0},{"code":"APG210825001","name":"Đoàn Duy Hào","al":0,"cl":0},{"code":"MEM210504021","name":"Lăng Văn Cừ","al":960,"cl":1341},{"code":"APG0241211001","name":"Nguyễn Thị Thanh Thúy","al":0,"cl":0},{"code":"APG0241125004","name":"Nguyễn Bích Tâm","al":0,"cl":0},{"code":"APG0241125006","name":"Trương Thị Kim Khánh","al":0,"cl":0},{"code":"APG0241119001","name":"Phạm Thị Thanh Ly","al":0,"cl":0},{"code":"APG0240814002","name":"Nguyễn Thị Ngọc Ánh","al":1238,"cl":0},{"code":"APG1240812002","name":"Nguyễn Thành Út","al":0,"cl":4553},{"code":"APG240603004","name":"Trần Mạnh Phước","al":0,"cl":0},{"code":"APG240401007","name":"Trương Thị Mỹ Linh","al":3840,"cl":178},{"code":"APG231201001","name":"Xích Thị Cẩm Tiên","al":0,"cl":0},{"code":"APG221025017","name":"Phạm Thị Thanh Ngân","al":5089,"cl":2953},{"code":"APG220906003","name":"Lê Dương Thục Trinh","al":0,"cl":0},{"code":"APG0241125005","name":"Phan Ngọc Trinh","al":0,"cl":0},{"code":"APG1240916004","name":"Bùi Chí Nam","al":16,"cl":0},{"code":"APG1240809002","name":"Nguyễn Công Tỉnh","al":1556,"cl":0},{"code":"APG1240808003","name":"Huỳnh Văn Hồng Thịnh","al":0,"cl":0},{"code":"APG1240715020","name":"Bá Đặng Ngọc Tiễn","al":0,"cl":0},{"code":"APG1240617007","name":"Võ Văn Vinh","al":2144,"cl":1525},{"code":"APG1240617008","name":"Lê Minh Trường","al":512,"cl":0},{"code":"APG240604001","name":"Lê Quốc Hiển","al":1418,"cl":0},{"code":"APG240514001","name":"Nguyễn Tấn Doanh","al":1486,"cl":0},{"code":"APG240312005","name":"Nguyễn Anh Tú","al":1771,"cl":0},{"code":"APG240304004","name":"Võ Dương Bảo Kiên","al":4033,"cl":0},{"code":"APG240115006","name":"Nguyễn Hải Nam","al":0,"cl":0},{"code":"APG240115005","name":"Nguyễn Hoài Nam","al":3383,"cl":3883},{"code":"APG231201002","name":"Trương Thành Quyền","al":906,"cl":0},{"code":"APG230810002","name":"Trần Văn Sơn","al":1944,"cl":239},{"code":"APG230703009","name":"Đinh Quang Trường","al":4423,"cl":0},{"code":"APG230427007","name":"Nguyễn Khánh Trân","al":2558,"cl":0},{"code":"APG230324012","name":"Phạm Như Ngọc Linh","al":1878,"cl":0},{"code":"APG230318001","name":"Lương Quốc Huy","al":1794,"cl":0},{"code":"APG230318003","name":"Nguyễn Đăng Huy","al":0,"cl":0},{"code":"APG230318006","name":"Phùng Công Vinh","al":3992,"cl":4665},{"code":"APG230318005","name":"Nguyễn Thái Nguyên","al":465,"cl":1080},{"code":"APG230318004","name":"Cổ Văn Dư","al":4202,"cl":998},{"code":"APG230318009","name":"Nguyễn Nhật Huy","al":1155,"cl":0},{"code":"APG220504005","name":"Trần Việt Hùng","al":263,"cl":1010},{"code":"APG221108005","name":"Nguyễn Tấn Thịnh","al":2879,"cl":631},{"code":"APG221101010","name":"Nguyễn Thanh Tùng","al":1461,"cl":0},{"code":"APG221025001","name":"Đặng Văn Dựng","al":480,"cl":4943},{"code":"APG221025002","name":"Phan Thanh Quân","al":3840,"cl":205},{"code":"APG221018020","name":"Hồ Thái Tâm","al":0,"cl":0},{"code":"APG221018018","name":"Bùi Văn Ánh","al":2785,"cl":0},{"code":"APG221012003","name":"Trần Quốc Vũ","al":0,"cl":0},{"code":"APG221007002","name":"Trương Quan Bình Kha","al":126,"cl":0},{"code":"APG220926002","name":"Huỳnh Minh Lộc","al":0,"cl":0},{"code":"APG220620001","name":"Lưu Thị Thu Hằng","al":0,"cl":0},{"code":"APG220509003","name":"Đồng Thanh Tùng","al":3541,"cl":3660},{"code":"DRW160128001","name":"Nguyễn Bá Hiệp","al":1840,"cl":2387},{"code":"DRW160118001","name":"Nguyễn Đức Tho","al":2641,"cl":108},{"code":"DRW160115001","name":"Nguyễn Hoàng Long","al":3170,"cl":56},{"code":"API191223002","name":"Lê Thanh Thành","al":127,"cl":0},{"code":"APG240805001","name":"Phạm Hoài Thu","al":876,"cl":0},{"code":"APG221004012","name":"Nguyễn Thị Huyền","al":1201,"cl":0},{"code":"APG220822003","name":"Nguyễn Thị Thảo Nguyên","al":5760,"cl":222},{"code":"APG220322026","name":"Cao Trịnh Phương Trâm","al":5325,"cl":1431},{"code":"APG210907001","name":"Huỳnh Thị Hồng Diễm","al":4177,"cl":1108},{"code":"APG210624001","name":"Lê Thị Thu Hằng","al":1903,"cl":0},{"code":"APG220819002","name":"Lương Văn Sang","al":3693,"cl":1049},{"code":"APG211116012","name":"Đinh Văn Hồi","al":4080,"cl":2753},{"code":"APG211109004","name":"Lê Minh Bằng","al":772,"cl":0},{"code":"APG211101001","name":"Lê Văn Huân","al":2818,"cl":240},{"code":"APG211012015","name":"Nguyễn Mạnh Khương","al":5760,"cl":3114},{"code":"APG210817006","name":"Nguyễn Văn Thịnh","al":480,"cl":7167},{"code":"APG210810006","name":"Trần Quốc Cường","al":2583,"cl":858},{"code":"APG210810005","name":"Huỳnh Quốc Nhiên","al":2637,"cl":0},{"code":"APG210727002","name":"Võ Quốc Thiên","al":4002,"cl":1115},{"code":"APG210629005","name":"Lê Hồng Thái","al":1440,"cl":5758},{"code":"APG240502006","name":"Trương Diệu Linh","al":0,"cl":0},{"code":"APG230419006","name":"Nguyễn Đức Thành","al":0,"cl":0},{"code":"APG230321014","name":"Bùi Xuân Duy","al":0,"cl":0},{"code":"DRW151228001","name":"Lê Thị Hà","al":471,"cl":0},{"code":"APG240423002","name":"Chu Thị Hằng","al":0,"cl":0},{"code":"APG220509002","name":"Hà Văn Đông","al":1073,"cl":1920},{"code":"API191007001","name":"Đàm Ngọc Bích","al":0,"cl":0},{"code":"APG221017002","name":"Nguyễn Trung Kiên","al":0,"cl":0},{"code":"APG221004001","name":"Nguyễn Thị Mai Lan","al":3931,"cl":0},{"code":"APG220405011","name":"Phạm Thị Bích Phượng","al":2259,"cl":0},{"code":"APG230921003","name":"Phạm Thị Mai","al":0,"cl":0},{"code":"APG230406028","name":"Nguyễn Thị Tươi","al":0,"cl":0},{"code":"APG220905004","name":"Nguyễn Huy Hào","al":0,"cl":0},{"code":"APG220309004","name":"Trần Thị Hoài Quyên","al":0,"cl":0},{"code":"APG220208005","name":"Bùi Thắng","al":0,"cl":0},{"code":"APG211012009","name":"Phạm Nhật Thu","al":0,"cl":0},{"code":"APG211012010","name":"Nguyễn Thị Ngọc Anh","al":0,"cl":0},{"code":"APS210120001","name":"Vũ Thị Ngọc Ánh","al":0,"cl":0},{"code":"APS200929004","name":"Nguyễn Thị Phúc Lan","al":0,"cl":0},{"code":"BGG200707001","name":"Đỗ Quỳnh Phương Anh","al":0,"cl":0},{"code":"APG0241010003","name":"Lê Kiều Anh","al":0,"cl":0},{"code":"APG240403002","name":"Trần Thị Hằng","al":0,"cl":0},{"code":"APG240228005","name":"Nguyễn Thuỷ Tiên","al":1275,"cl":530},{"code":"APG230919005","name":"Nguyễn Thị Phương Uyên","al":2444,"cl":0},{"code":"APG230919008","name":"Đỗ Trần Quỳnh Nga","al":0,"cl":0},{"code":"APG230509002","name":"Nguyễn Thị Thanh Loan","al":339,"cl":0},{"code":"APG230328001","name":"Nguyễn Thị Hường","al":673,"cl":1490},{"code":"APG220816005","name":"Nguyễn Ngọc Hiền","al":0,"cl":0},{"code":"APG0241010001","name":"Trịnh Thanh Thảo","al":0,"cl":0},{"code":"APG0241008002","name":"Đỗ Phương Thảo","al":0,"cl":0},{"code":"APG0241007005","name":"Nguyễn Thị Như Quỳnh","al":0,"cl":0},{"code":"APS170213001","name":"Nguyễn Đức Hà","al":0,"cl":0},{"code":"APG221129004","name":"Chu Thị Diệu Linh","al":0,"cl":289},{"code":"APG220517002","name":"Võ Thị Thu Lượng","al":3086,"cl":1060},{"code":"BGG200908012","name":"Nguyễn Hồng Ngọc","al":0,"cl":0},{"code":"APG230504002","name":"Trần Quang Minh Lộc","al":0,"cl":0},{"code":"APG0241104001","name":"Lê Thị Ngọc Trinh","al":0,"cl":0},{"code":"APG0240919003","name":"Phạm Thị Khánh Vy","al":0,"cl":0},{"code":"API191028006","name":"Trần Thúy Hà","al":972,"cl":0},{"code":"APG220822005","name":"Vũ Hương Giang","al":0,"cl":0},{"code":"APG220809016","name":"Lương Thị Như Nguyệt","al":0,"cl":0},{"code":"BGG201103006","name":"Nguyễn Thị Thuỳ Ny","al":2013,"cl":0},{"code":"BGG200428001","name":"Trần Thị Huệ","al":1125,"cl":0},{"code":"APG220704002","name":"Nguyễn Thị Thúy","al":0,"cl":0},{"code":"APG0241223003","name":"Nguyễn Phương Huyền My","al":0,"cl":0},{"code":"APG1241014002","name":"Trần Ngọc Hải","al":0,"cl":669},{"code":"APG240719003","name":"Nguyễn Thành Đạt","al":0,"cl":0},{"code":"APG240719002","name":"Cao Đình Trường","al":263,"cl":150},{"code":"APG240719001","name":"Nguyễn Đức Quý","al":0,"cl":0},{"code":"APG240701003","name":"Trương Diệu Anh","al":0,"cl":0},{"code":"APG240521001","name":"Vũ Duy Linh","al":0,"cl":0},{"code":"APG240401006","name":"Lê Ngọc Dinh","al":4320,"cl":615},{"code":"APG240315002","name":"Đào Duy Anh","al":2518,"cl":960},{"code":"API060901004","name":"Phạm Hoài Phương","al":0,"cl":0},{"code":"APS150107001","name":"Nguyễn Phương Dung","al":2301,"cl":0},{"code":"API200420014","name":"Lương Tuấn Tú","al":0,"cl":1596},{"code":"API200706001","name":"Nguyễn Quang Đạt","al":0,"cl":4652},{"code":"API201229001","name":"Vũ Danh Thắng","al":0,"cl":1352},{"code":"API200203002","name":"Phạm Quang Ninh","al":1249,"cl":1299},{"code":"API181101003","name":"Nguyễn Thị Hợp","al":0,"cl":0},{"code":"API181101002","name":"Ngô Thị Tại","al":675,"cl":0},{"code":"API170920003","name":"Nguyễn Thị Mở","al":44,"cl":0},{"code":"API170906002","name":"Nguyễn Thị Hường","al":0,"cl":0},{"code":"API170906001","name":"Hoàng Thị Loan","al":0,"cl":479},{"code":"APG220818001","name":"Nguyễn Đỗ Hoàng Lan","al":0,"cl":0},{"code":"APG220818002","name":"Zamiel Vanfleteren","al":0,"cl":0},{"code":"APG220207001","name":"Nguyễn Mạnh Cường","al":0,"cl":0},{"code":"API190819001","name":"Nguyễn Thị Thơm","al":0,"cl":0},{"code":"API190812004","name":"Nguyễn Thị Phương Linh","al":536,"cl":0},{"code":"API190805001","name":"Trần Thanh Huyền","al":0,"cl":0},{"code":"API170301002","name":"Nguyễn Phương Ngân","al":0,"cl":2118},{"code":"API181112002","name":"Nguyễn Quốc Anh","al":0,"cl":0},{"code":"API180507001","name":"Vũ Văn Dũng","al":0,"cl":0},{"code":"API161220001","name":"Nguyễn Việt Hoàng","al":0,"cl":0},{"code":"APG240408001","name":"Trần Thị My","al":0,"cl":0},{"code":"APG220613002","name":"Hoàng Kim Hằng","al":0,"cl":0},{"code":"APG220322001","name":"Vũ Thị Diệu Lê","al":29,"cl":0},{"code":"API190729003","name":"Đặng Thị Hoài Anh","al":1476,"cl":0},{"code":"API190311003","name":"Phạm Thị Châu","al":74,"cl":0},{"code":"API180601003","name":"Vũ Trung Kiên","al":0,"cl":1426},{"code":"APG231017002","name":"Nguyễn Thị Hồng Hạnh","al":0,"cl":0},{"code":"API190401001","name":"Nguyễn Đức Quân","al":4329,"cl":0},{"code":"API170317001","name":"Lê Ngọc Hiền","al":0,"cl":0},{"code":"API141011001","name":"Nguyễn Thị Phương Thoa","al":2527,"cl":0},{"code":"API210330008","name":"Trần Phan Linh Chi","al":0,"cl":0},{"code":"API190708002","name":"Vũ Thị Thanh Loan","al":1141,"cl":0},{"code":"API181126002","name":"Ngô Thị Thanh Sắc","al":0,"cl":0},{"code":"API180201001","name":"Nguyễn Thị Vân Anh","al":697,"cl":0},{"code":"API080101001","name":"Nguyễn Hoài Giang","al":0,"cl":0},{"code":"APG240404001","name":"Nguyễn Hữu Quang Minh","al":0,"cl":0},{"code":"API190724001","name":"Đoàn Hải Lâm","al":0,"cl":0},{"code":"API170605001","name":"Đặng Minh Tuấn","al":0,"cl":0},{"code":"API170821001","name":"Cao Thị Minh Châu","al":134,"cl":330},{"code":"APG220208003","name":"Ngô Quốc Mạnh","al":0,"cl":1675},{"code":"API191111002","name":"Phạm Đức Công","al":883,"cl":855},{"code":"API180507002","name":"Nguyễn Hồng Vinh","al":0,"cl":0},{"code":"API170301001","name":"Trần Văn Công","al":1954,"cl":0},{"code":"APG211102005","name":"Đào Thị Hiền","al":0,"cl":0},{"code":"APS141118001","name":"Nguyễn Thị Thanh","al":0,"cl":0},{"code":"APS090401001","name":"Nguyễn Đức Quân","al":0,"cl":0},{"code":"API060901001","name":"Nguyễn Đỗ Lăng","al":7200,"cl":0},{"code":"APG240401003","name":"Vũ Thị Thanh Huyền","al":0,"cl":0},{"code":"APS070528001","name":"Phạm Thị Đức Việt","al":0,"cl":0},{"code":"APS151001001","name":"Nguyễn Phước Thiện","al":2702,"cl":0},{"code":"APS090112001","name":"Dương Thị Ngọc Mận","al":297,"cl":0},{"code":"APS070615001","name":"Trần Thị Huỳnh Mai","al":5934,"cl":0},{"code":"APS070502001","name":"Nguyễn Thanh Hiền","al":1998,"cl":0},{"code":"APG240612001","name":"Nguyễn Việt Hà","al":0,"cl":0},{"code":"APG240502005","name":"Nguyễn Thị Hồng Lam","al":0,"cl":0},{"code":"APG230919006","name":"Hoàng Văn Bút","al":0,"cl":0},{"code":"APG220705008","name":"Phan Đình Lai","al":0,"cl":0},{"code":"APG220425001","name":"Đỗ Văn Linh","al":0,"cl":0},{"code":"APG211102003","name":"Nguyễn Văn Huy","al":0,"cl":917},{"code":"APG210921004","name":"Đỗ Văn Luân","al":0,"cl":0},{"code":"APG210713006","name":"Nguyễn Huy Mạnh","al":0,"cl":0},{"code":"APS180205001","name":"Hồ Sỹ Quyết","al":0,"cl":0},{"code":"APS090811001","name":"Nguyễn Văn Hào","al":1127,"cl":0},{"code":"APS210330009","name":"Nguyễn Thị Minh Trang","al":719,"cl":3},{"code":"APS190923001","name":"Lê Minh Hằng","al":0,"cl":0},{"code":"APS170919001","name":"Hỏa Thị Hòe","al":697,"cl":868},{"code":"APS070101001","name":"Đinh Thị Thu Hằng","al":0,"cl":0},{"code":"APS160328001","name":"Nguyễn Thị Ánh","al":0,"cl":0},{"code":"APS180828001","name":"Nguyễn Thị Hiền","al":2423,"cl":0},{"code":"API180501001","name":"Mai Thúy Vân","al":0,"cl":0},{"code":"API110624001","name":"Lê Hồng Nam","al":2190,"cl":4480},{"code":"API191118002","name":"Đậu Thị Thảo","al":210,"cl":0},{"code":"API181013008","name":"Nguyễn Thị Ngọc Hà","al":2063,"cl":0},{"code":"APS160606001","name":"Phạm Thị Tươi","al":2863,"cl":0},{"code":"APG0240904004","name":"Vũ Thị Dinh","al":0,"cl":0},{"code":"APG211214003","name":"Nguyễn Thu Hương","al":1573,"cl":0},{"code":"APS180423001","name":"Trần Thị Nguyệt","al":0,"cl":0},{"code":"APS161125001","name":"Nguyễn Thu Phương","al":2713,"cl":0},{"code":"APG1241205001","name":"Lã Trọng Nguyên","al":0,"cl":0},{"code":"APG220728001","name":"Vũ Thị Liên","al":0,"cl":0},{"code":"APG220620004","name":"Vũ Ngọc Sơn","al":0,"cl":0},{"code":"API210504002","name":"Nguyễn Đoàn Tùng","al":0,"cl":0},{"code":"APG240322003","name":"Nguyễn Thị Phượng","al":1517,"cl":0},{"code":"APITD200903001","name":"Dương Thị Luyến","al":240,"cl":0},{"code":"API191111007","name":"Hà Thị Mận","al":720,"cl":0},{"code":"API191028002","name":"Đậu Thị Huyền Lương","al":0,"cl":0},{"code":"API150501002","name":"Nguyễn Xuân Hiếu","al":0,"cl":0},{"code":"API150501001","name":"Tạ Trung Kiên","al":1849,"cl":0},{"code":"APG0241125003","name":"Nguyễn Thanh Lam","al":0,"cl":0},{"code":"IDJ170728001","name":"Đinh Quốc Đức","al":0,"cl":0},{"code":"IDJ160101001","name":"Lã Thị Quy","al":0,"cl":0},{"code":"API060901002","name":"Huỳnh Thị Mai Dung","al":7200,"cl":0},{"code":"API160922002","name":"Nguyễn Ngọc Dương","al":4363,"cl":0},{"code":"IDJ191223004","name":"Đỗ Văn Tú","al":247,"cl":3360},{"code":"APG221005001","name":"Nguyễn Sỹ Biển","al":0,"cl":6420},{"code":"APG220705011","name":"Lê Xuân Hào","al":0,"cl":516},{"code":"APG210819001","name":"Phùng Anh Vũ","al":0,"cl":0},{"code":"IDJ210223005","name":"Nguyễn Trường Hùng","al":663,"cl":2748},{"code":"API181112003","name":"Nguyễn Ngọc Diệp","al":0,"cl":0},{"code":"APG210810002","name":"Nguyễn Đình Chí","al":0,"cl":0},{"code":"IDJ200817001","name":"Nguyễn Thế Mạnh","al":5760,"cl":1920},{"code":"IDJ191024001","name":"Trần Thế Đương","al":0,"cl":0},{"code":"IDJ191024002","name":"Trần Thị Hảo","al":0,"cl":0},{"code":"API200805001","name":"Trịnh Quang Dũng","al":0,"cl":0},{"code":"IDJ191209003","name":"Nguyễn Quốc Vương Anh","al":0,"cl":0},{"code":"APG230419004","name":"Hồ Sỹ Hiếu","al":0,"cl":0},{"code":"APG240222005","name":"Vương Quang Huy","al":0,"cl":0},{"code":"APG230419005","name":"Phạm Minh Đức","al":0,"cl":0},{"code":"APG230321013","name":"Nguyễn Đức Anh","al":1659,"cl":0},{"code":"APG221101003","name":"Lê Quốc Bảo","al":0,"cl":0},{"code":"APG230811003","name":"Nguyễn Thị Nguyệt","al":412,"cl":0},{"code":"APG230801001","name":"Lê Thị Trúc Linh","al":0,"cl":0},{"code":"APG210713008","name":"Lê Thị Thu Trang","al":0,"cl":0},{"code":"IDJ200714003","name":"Hoàng Thị Hường","al":0,"cl":0},{"code":"IDJ200615005","name":"Nguyễn Khánh Linh","al":0,"cl":0},{"code":"APG211005008","name":"Nguyễn Văn Huy","al":1159,"cl":0},{"code":"IDJ210601001","name":"Phùng Nguyễn Kim Long","al":0,"cl":0},{"code":"API180502003","name":"Lê Thanh Tùng","al":1740,"cl":0},{"code":"APG220719003","name":"Đặng Hoàng Long","al":286,"cl":125},{"code":"API210112005","name":"Nguyễn Đức Trung","al":0,"cl":0},{"code":"API200622001","name":"Nguyễn Đình Huy","al":0,"cl":0},{"code":"APG220524003","name":"Nguyễn Quang Học","al":0,"cl":0},{"code":"APG210928010","name":"Nguyễn Thị Mỹ Linh","al":0,"cl":0},{"code":"IDJ181126001","name":"Nguyễn Hữu Đạt","al":0,"cl":0},{"code":"DRW171101002","name":"Nguyễn Ngọc Diệp","al":205,"cl":0},{"code":"DRW150609001","name":"Đỗ Thị Hoa","al":0,"cl":0},{"code":"APG231023003","name":"Vũ Hoàng Anh","al":0,"cl":72},{"code":"API180601002","name":"Lê Thị Hồng","al":0,"cl":0},{"code":"APG220419004","name":"Hồ Mạnh Quân","al":0,"cl":0},{"code":"IDJ200615003","name":"Ngô Thành Trung","al":0,"cl":0},{"code":"IDJ200629003","name":"Trịnh Công Anh","al":0,"cl":0},{"code":"IDJ210420001","name":"Nguyễn Thị Hằng","al":0,"cl":0},{"code":"KB210608003","name":"Trần Duy Tín","al":0,"cl":0},{"code":"APG240419001","name":"Vũ Ngọc Mai","al":489,"cl":0},{"code":"APG230705004","name":"Nguyễn Thu Huyền","al":0,"cl":0},{"code":"APG230627011","name":"Nguyễn Thị Lan Anh","al":0,"cl":0},{"code":"APG230314020","name":"Hà Thùy Ly","al":0,"cl":0},{"code":"API200908007","name":"Vũ Thị Hồng Nhung","al":0,"cl":0},{"code":"APG220420006","name":"Nguyễn Tài Dũng","al":2392,"cl":0},{"code":"APG240819013","name":"Nguyễn Phương Thảo","al":0,"cl":0},{"code":"APG211001002","name":"Lương Mỹ Duyên","al":0,"cl":0},{"code":"APG221108003","name":"Nguyễn Huyền Trang","al":0,"cl":0},{"code":"APG231102005","name":"Nguyễn Thị Uyển Nhi","al":0,"cl":0},{"code":"APG211012013","name":"Nguyễn Thu Thảo","al":0,"cl":0},{"code":"APG211005005","name":"Phạm Thị Nhị","al":0,"cl":0},{"code":"APG1241007004","name":"Lê Anh Tú","al":0,"cl":0},{"code":"APG1240916002","name":"Nguyễn Trường Long","al":339,"cl":0},{"code":"APG240812001","name":"Triệu Minh Thảo","al":0,"cl":0},{"code":"APG240801001","name":"Trần Xuân Dũng","al":0,"cl":0},{"code":"APG231020005","name":"Nguyễn Thị Giang","al":0,"cl":0},{"code":"APG230414002","name":"Lê Thị Huyền","al":0,"cl":0},{"code":"APG210422003","name":"Lý Thị Mai","al":0,"cl":0},{"code":"APG0241024001","name":"Bùi Lê Trà My","al":0,"cl":0},{"code":"APG0241106003","name":"Hoàng Phương Thảo","al":0,"cl":0},{"code":"APG0241014003","name":"Nguyễn Thị Yến","al":0,"cl":0},{"code":"APG0240926001","name":"Lê Diễm Quỳnh","al":0,"cl":0},{"code":"APG1241028003","name":"Trần Việt Hoàn","al":0,"cl":0},{"code":"APG231009001","name":"Vũ Thị Lệ Quỳnh","al":0,"cl":0},{"code":"API190422002","name":"Nguyễn Thị Huyền","al":98,"cl":0},{"code":"APG1241112001","name":"Vũ Minh Hiếu","al":0,"cl":0},{"code":"APG1241111004","name":"Trương Văn Chiến","al":0,"cl":0},{"code":"APG240527002","name":"Ngô Xuân Thế","al":337,"cl":440},{"code":"APG231108004","name":"Đỗ Thị Ngọc Hà","al":842,"cl":960},{"code":"APG1240919002","name":"Nguyễn Quang Minh","al":0,"cl":0},{"code":"APG240723001","name":"Tạ Tuấn Nghĩa","al":0,"cl":0},{"code":"API210105001","name":"Nguyễn Hà My","al":832,"cl":4714},{"code":"API190520001","name":"Phạm Nguyễn Hải Ninh Linh Ly","al":0,"cl":0},{"code":"APG0241014001","name":"Lý Hoài Thu","al":0,"cl":756},{"code":"APG240827002","name":"Phạm Thị Linh","al":853,"cl":423},{"code":"APG240814001","name":"Vũ Mạnh Hùng","al":390,"cl":36},{"code":"APG240813002","name":"Nguyễn Mạnh Cường","al":394,"cl":511},{"code":"APG240806001","name":"Lê Trọng Kiên","al":0,"cl":0},{"code":"APG240515001","name":"Đoàn Thị Thu Huệ","al":0,"cl":0},{"code":"APG240502009","name":"Lê Ngọc Chương","al":0,"cl":0},{"code":"APG240502008","name":"Vũ Diệu Linh","al":0,"cl":643},{"code":"APG240423001","name":"Nguyễn Văn Tiến","al":0,"cl":176},{"code":"APG230606002","name":"Nguyễn Thị Ngọc Diệp","al":156,"cl":539},{"code":"APG221018013","name":"Phạm Kiều Duyên","al":0,"cl":0},{"code":"APG220601006","name":"Đỗ Văn Trường","al":0,"cl":413},{"code":"APG220516009","name":"Hoàng Thị Mến","al":0,"cl":946},{"code":"APG231005011","name":"Bùi Vũ Hoa Phượng","al":0,"cl":756},{"code":"APG240624001","name":"Nông Thị Mỹ Hạnh","al":0,"cl":0},{"code":"APG230907001","name":"Đỗ Thị Tuyết","al":617,"cl":0},{"code":"APG220906007","name":"Đàm Bảo Ngọc","al":0,"cl":0},{"code":"IDJ190819002","name":"Hoàng Thị Huyền","al":1662,"cl":0},{"code":"APG0241111003","name":"Nguyễn Thị Trâm","al":0,"cl":0},{"code":"APG0241104004","name":"Nguyễn Thúy Nga","al":0,"cl":0},{"code":"APG1241028002","name":"Lê Thành Minh","al":0,"cl":0},{"code":"APG0241021001","name":"Lê Thị Thu Thuỳ","al":0,"cl":0},{"code":"APG1241007001","name":"Khúc Xuân Nam","al":0,"cl":0},{"code":"API181003001","name":"Trần Thanh Toàn","al":1302,"cl":3781},{"code":"APG0241225001","name":"Nguyễn Trần Thảo My","al":0,"cl":0},{"code":"APG240701001","name":"Huỳnh Thị Huỳnh Như","al":304,"cl":0},{"code":"APG240603003","name":"Ngô Thị Tuyến","al":0,"cl":1036},{"code":"APG230509001","name":"Lê Thị Hồng Nhung","al":0,"cl":0},{"code":"APG240124001","name":"Nguyễn Thị Tuyết Nhung","al":0,"cl":0},{"code":"APG231225001","name":"Đỗ Thu Phương","al":0,"cl":2528},{"code":"APG231113006","name":"Lưu Bảo Hân","al":0,"cl":33},{"code":"APG230619006","name":"Ngô Thị Hương Ly","al":353,"cl":3349},{"code":"APG230529001","name":"Nguyễn Tiến Hiệp","al":0,"cl":503},{"code":"APG230403002","name":"Đặng Thanh Hòa","al":0,"cl":0},{"code":"APG220712013","name":"Nguyễn Lê Huy","al":0,"cl":0},{"code":"APG1241226001","name":"Lê Trung Hậu","al":0,"cl":0},{"code":"APG1241224001","name":"Cung Anh Phong","al":0,"cl":0},{"code":"APG240502002","name":"Đặng Thị Như Hiếu","al":0,"cl":404},{"code":"APG231031001","name":"Nguyễn Thị Yến Nhi","al":0,"cl":0},{"code":"APG230605001","name":"Nguyễn Thị Ngọc Xuyến","al":1259,"cl":530},{"code":"APG240604002","name":"Nguyễn Trần Thục Vy","al":0,"cl":414},{"code":"APG240527001","name":"Trần Bình Đức","al":206,"cl":0},{"code":"APG240506001","name":"Ngô Thị Diệu Linh","al":378,"cl":0},{"code":"APG240313004","name":"Nguyễn Hạnh Nguyệt","al":0,"cl":1897},{"code":"APG230619007","name":"Lương Thị Thúy Quỳnh","al":0,"cl":0},{"code":"APG220823001","name":"Đinh Thị Mỹ Linh","al":819,"cl":676},{"code":"MAD190506009","name":"Đinh Thị Mỹ Linh","al":0,"cl":171},{"code":"APG0241210001","name":"Lê Thị Hồng Nhung","al":0,"cl":0},{"code":"APG1240515011","name":"Nìm Chính Thiện","al":34,"cl":0},{"code":"APG221226009","name":"Nguyễn Thị Đoan Trang","al":5614,"cl":157},{"code":"APG221226004","name":"Nguyễn Thị Hiếu","al":3444,"cl":0},{"code":"APG221226001","name":"Ngô Thị Hảo","al":2581,"cl":189},{"code":"APG221227001","name":"Trang Bảo Toàn","al":745,"cl":1},{"code":"APG221229002","name":"Nguyễn Minh Tâm","al":1203,"cl":49},{"code":"APG230217001","name":"Nguyễn Thị Trúc Dung","al":1199,"cl":6},{"code":"APG230217002","name":"Nguyễn Thị Ly Bâng","al":1741,"cl":0},{"code":"APG230217003","name":"Nguyễn Thị Trúc Ngân","al":971,"cl":36},{"code":"APG230217004","name":"Nguyễn Thị Hạnh","al":3894,"cl":29},{"code":"APG230217006","name":"Nguyễn Thị Gái","al":4019,"cl":29},{"code":"APG230217007","name":"Đào Thị Kim Oanh","al":3363,"cl":473},{"code":"APG230201007","name":"Nguyễn Văn Quốc","al":2182,"cl":140},{"code":"APG230202003","name":"Huỳnh Thị Xuân Mai","al":3828,"cl":58},{"code":"APG230316004","name":"Lê Thị Ngọc Đẹp","al":783,"cl":0},{"code":"APG230324003","name":"Nguyễn Thị Mai","al":3360,"cl":420},{"code":"APG230324011","name":"Nguyễn Thị Thi","al":6240,"cl":5230},{"code":"APG230321011","name":"Phạm Thị Thùy Linh","al":1755,"cl":48},{"code":"APG230320016","name":"Nguyễn Phước Vinh","al":1623,"cl":410},{"code":"APG230320015","name":"Trần Anh Vũ","al":2586,"cl":278},{"code":"APG230317002","name":"Nguyễn Thị Minh Ngân","al":4080,"cl":80},{"code":"APG230321001","name":"Nguyễn Thị Thu Linh","al":4506,"cl":275},{"code":"APG230321005","name":"Trần  Huy","al":5465,"cl":4629},{"code":"APG230321006","name":"Nguyễn Thy Dáng Uyên","al":5714,"cl":3367},{"code":"APG230315004","name":"Nguyễn Thị Tố Nương","al":5734,"cl":675},{"code":"APG230323003","name":"Nguyễn Thị Hồng Hiền","al":1193,"cl":5},{"code":"APG230316013","name":"Lê Thị Chàm","al":3481,"cl":70},{"code":"APG230316014","name":"Đoàn Thị Mỹ Nhung","al":3762,"cl":375},{"code":"APG230316016","name":"Đoàn Thị Ba","al":3763,"cl":0},{"code":"APG230316017","name":"Lê Thị Thanh Yến","al":1277,"cl":0},{"code":"APG230316011","name":"Nguyễn Thị Ngọc Triệu","al":3763,"cl":30},{"code":"APG230316009","name":"Phùng Thị Thùy Trang","al":5683,"cl":1932},{"code":"APG230316010","name":"Phạm Thị Mỹ Dung","al":3575,"cl":3},{"code":"APG230411002","name":"Phan Đình Trung","al":6049,"cl":11713},{"code":"APG230406011","name":"Nguyễn Thị Đoan Trinh","al":1854,"cl":163},{"code":"APG230406013","name":"Lê Thị Chương","al":1562,"cl":235},{"code":"APG230406015","name":"Nguyễn Thị Lượm","al":4739,"cl":63},{"code":"APG230407003","name":"Lê Thị Cẩm Linh","al":3219,"cl":113},{"code":"APG230407004","name":"Trần Thị Hằng","al":960,"cl":20},{"code":"APG230407008","name":"Phạm Thị Tới","al":5405,"cl":957},{"code":"APG230407009","name":"Bùi Thị Xuân Quý","al":1164,"cl":242},{"code":"APG230417005","name":"Trần Thị Loan","al":3735,"cl":33},{"code":"APG230427004","name":"Nguyễn Hồng Đảm","al":5726,"cl":3840},{"code":"APG230404013","name":"Huỳnh Thị Thanh Kiều","al":741,"cl":455},{"code":"APG230404011","name":"Trần Thị Ngọc Hoà","al":4767,"cl":818},{"code":"APG230407011","name":"Lê Thị Thu Hương","al":5545,"cl":1676},{"code":"APG230411005","name":"Trần Thế Qua","al":5082,"cl":534},{"code":"APG230411006","name":"Nguyễn Thị Ngọc Bích","al":2890,"cl":1387},{"code":"APG230411008","name":"Huỳnh Thị Hồng Vân","al":5632,"cl":330},{"code":"APG230411009","name":"Đồng Gia Huy","al":4917,"cl":2978},{"code":"APG230411010","name":"Trần Hữu Tạo","al":4916,"cl":4048},{"code":"APG230421005","name":"Nguyễn Thị Mỹ Uyên","al":5000,"cl":4341},{"code":"APG230427006","name":"Nguyễn Thị Ngọc Ước","al":5160,"cl":800},{"code":"APG230406016","name":"Nguyễn Thị Anh","al":568,"cl":0},{"code":"APG230406017","name":"Lê Thị Ngọc Lành","al":2879,"cl":5628},{"code":"APG230417007","name":"Đặng Thị Kim Phương","al":5040,"cl":900},{"code":"APG230406021","name":"Huỳnh Ngọc Thái Yên","al":61,"cl":1},{"code":"APG230407013","name":"Lê Thị Thảo","al":3972,"cl":403},{"code":"APG230412011","name":"Lâm Thanh Hải","al":5167,"cl":1200},{"code":"APG230417009","name":"Lê Thị Kim Hương","al":622,"cl":20},{"code":"APG230417011","name":"Nguyễn Duy Khang","al":4703,"cl":220},{"code":"APG230405014","name":"Lê Tấn Đạt","al":615,"cl":264},{"code":"APG230405015","name":"Nguyễn Tiềng Mộng","al":3296,"cl":240},{"code":"APG230412016","name":"Nguyễn Thành Tất","al":2720,"cl":308},{"code":"APG230404017","name":"Nguyễn Minh Thức","al":1607,"cl":0},{"code":"APG230406038","name":"Hà Huy Đồng","al":1534,"cl":303},{"code":"APG230407018","name":"Lê Văn Hùng","al":1392,"cl":114},{"code":"APG230407019","name":"Võ Văn Tâm","al":856,"cl":97},{"code":"APG230407020","name":"Lương Thanh Trúc","al":381,"cl":445},{"code":"APG230409002","name":"Nguyễn Văn Sen","al":1534,"cl":404},{"code":"APG230409011","name":"Trương Phan Tấn Hiển","al":1403,"cl":50},{"code":"APG230409012","name":"Nguyễn Thị Ngọc Hường","al":6192,"cl":1846},{"code":"APG230409013","name":"Nguyễn Thị Lệ Hà","al":4683,"cl":2901},{"code":"APG230417015","name":"Trần Tấn Cang","al":1197,"cl":67},{"code":"APG230421003","name":"La Thị Hiền","al":2079,"cl":255},{"code":"APG230427008","name":"Nguyễn Thị Hồng Kim","al":590,"cl":18},{"code":"APG230405011","name":"Lại Thanh Đông","al":2109,"cl":76},{"code":"APG230405013","name":"Võ Thị Như Phượng","al":5086,"cl":662},{"code":"APG230412006","name":"Lê Minh Tuấn","al":543,"cl":3},{"code":"APG230427009","name":"Võ Dương Vinh","al":4267,"cl":399},{"code":"APG230412007","name":"Trần Thị Bé","al":2308,"cl":20},{"code":"APG230525008","name":"Nguyễn Lý Thiên Ngân","al":375,"cl":81},{"code":"APG230508002","name":"Hoàng Ngọc Kim","al":228,"cl":6},{"code":"APG230517002","name":"Nguyễn Hồng Vũ","al":170,"cl":0},{"code":"APG230511004","name":"Huỳnh Thị Bé Nhi","al":3128,"cl":333},{"code":"APG230515004","name":"Huỳnh Phúc Chiến","al":4257,"cl":4159},{"code":"APG230517004","name":"Nguyễn Thị Tiền","al":5158,"cl":1953},{"code":"APG230515007","name":"Đào Minh Hoa Niệm","al":3363,"cl":371},{"code":"APG230518001","name":"Lê Nguyên Sôn","al":1204,"cl":131},{"code":"APG230515006","name":"Tạ Quang Huy","al":2152,"cl":5},{"code":"APG230517005","name":"Trần Diệp Thảo Nguyên","al":3919,"cl":457},{"code":"APG230517006","name":"Nguyễn Văn Duy","al":1585,"cl":107},{"code":"APG230525006","name":"Nguyễn Thị Phương Kiều","al":4059,"cl":31},{"code":"APG230525009","name":"Trần Thị Hồng Hiếu","al":1564,"cl":58},{"code":"APG230511005","name":"Phan Thị Mỹ Hồng","al":4258,"cl":237},{"code":"APG230523001","name":"Trần Thanh Vàng","al":3180,"cl":447},{"code":"APG230526002","name":"Nguyễn Minh Tùng","al":2632,"cl":28},{"code":"APG230526003","name":"Nguyễn Minh Hiếu","al":359,"cl":0},{"code":"APG230526004","name":"Trần Phương Vương","al":3018,"cl":666},{"code":"APG230515011","name":"Nguyễn Thị Ngọc Hà","al":2998,"cl":29},{"code":"APG230517001","name":"Trần Thị Ánh Tâm","al":2704,"cl":549},{"code":"APG230601010","name":"Nguyễn Tiền Phong","al":2164,"cl":232},{"code":"APG230601011","name":"Nguyễn Thị Hà","al":3840,"cl":0},{"code":"APG230619008","name":"Lê Thị Nguyên Sa","al":925,"cl":32},{"code":"APG230619009","name":"Trần Minh Tuấn","al":2934,"cl":74},{"code":"APG230619011","name":"Phạm Thị Yến Vân","al":5455,"cl":3093},{"code":"APG230619014","name":"Lê Hữu Tấn","al":4391,"cl":179},{"code":"APG230619005","name":"Hồ Đắc Dũng","al":127,"cl":43},{"code":"APG230620002","name":"Huỳnh Thị Bích","al":4320,"cl":163},{"code":"APG230624005","name":"Trần Thị Kim Mĩ","al":3393,"cl":477},{"code":"APG230624007","name":"Nguyễn Thị Thanh Đài","al":3436,"cl":7},{"code":"APG230624008","name":"Huỳnh Thị Ngọc Thắm","al":3840,"cl":16},{"code":"APG230626002","name":"Nguyễn Thị Diễm Hương","al":1550,"cl":40},{"code":"APG230608004","name":"Lê Thị Thúy Vy","al":4981,"cl":467},{"code":"APG230619015","name":"Huỳnh Văn Hoàng","al":4646,"cl":5016},{"code":"APG230619018","name":"Nguyễn Văn An","al":3802,"cl":620},{"code":"APG230624014","name":"Nguyễn Ngọc Hưng","al":4780,"cl":1636},{"code":"APG230626003","name":"Lê Thị Bích Quyên","al":5542,"cl":4564},{"code":"APG230627002","name":"Nguyễn Văn Minh","al":4536,"cl":116},{"code":"APG230601013","name":"Trịnh Mai Hoàng Nhiên","al":2834,"cl":0},{"code":"APG230609002","name":"Đồng Thanh Lâm","al":5760,"cl":2095},{"code":"APG230621001","name":"Nguyễn Văn Kính","al":2400,"cl":209},{"code":"APG230601014","name":"Đoàn Thị Thanh Nhàn","al":1920,"cl":503},{"code":"APG230627008","name":"Nguyễn Đại Lợi","al":4896,"cl":2662},{"code":"APG230609004","name":"Nguyễn Linh Hoàng","al":196,"cl":0},{"code":"APG230623004","name":"Trần Xuân Quang","al":3309,"cl":45},{"code":"APG230615006","name":"Nguyễn Thị Ngọc Mong","al":3641,"cl":9},{"code":"APG230712001","name":"Trần Vi Đan","al":132,"cl":4},{"code":"APG230703005","name":"Nông Văn Quý","al":1920,"cl":23},{"code":"APG230708001","name":"Trần Duy Linh","al":1332,"cl":472},{"code":"APG230703006","name":"Võ Thị Thanh Kiều","al":5729,"cl":4525},{"code":"APG230721003","name":"Nguyễn Đức Hòa","al":5479,"cl":3204},{"code":"APG230712006","name":"Dương Thị Minh Trân","al":959,"cl":265},{"code":"APG230721001","name":"Phạm Quốc Bảo","al":606,"cl":0},{"code":"APG230703007","name":"Lương Trần Cường","al":5760,"cl":946},{"code":"APG230712007","name":"Nguyễn Thị Trà Mi","al":2554,"cl":155},{"code":"APG230712009","name":"Nguyễn Tú Nhi","al":399,"cl":119},{"code":"APG230708002","name":"Quách Tấn Khương","al":6132,"cl":5415},{"code":"APG230720001","name":"Võ Tấn Tuyển","al":4986,"cl":23},{"code":"APG230720002","name":"Nguyễn Tấn Trung","al":5175,"cl":226},{"code":"APG230801002","name":"Nguyễn Công Hoàng","al":991,"cl":60},{"code":"APG230809001","name":"Vi Thị Từ","al":317,"cl":372},{"code":"APG230823001","name":"Lê Ngọc Huy","al":5760,"cl":7168},{"code":"APG230826001","name":"Bùi Anh Vương","al":5760,"cl":4273},{"code":"APG230818002","name":"Trương Minh Trí","al":2494,"cl":169},{"code":"APG230823002","name":"Nguyễn Văn Lộc","al":6240,"cl":7285},{"code":"APG230801003","name":"Diệp Minh Luân","al":5760,"cl":2524},{"code":"APG230905002","name":"Dương Thanh Tâm","al":5712,"cl":4081},{"code":"APG220819001","name":"Đàm Duy Trường","al":1312,"cl":49},{"code":"APG230914001","name":"Nguyễn Văn Hậu","al":2208,"cl":225},{"code":"APG230905003","name":"Đặng Thị Kim Hiệp","al":5529,"cl":1131},{"code":"APG230919002","name":"Nguyễn Ngọc Phương Trúc","al":4410,"cl":455},{"code":"APG230919004","name":"Lý Trương Thùy Trang","al":3591,"cl":1134},{"code":"APG231127001","name":"Lê Minh Nghĩa","al":-4,"cl":58},{"code":"APG231225003","name":"Nguyễn Triều Hải Đăng","al":6348,"cl":9482},{"code":"APG231225004","name":"Phạm Thị Huỳnh Như","al":420,"cl":47},{"code":"APG231204001","name":"Trần Nguyễn Nhựt Huy","al":1634,"cl":231},{"code":"APG240112001","name":"Đỗ Khắc Gia Anh","al":4587,"cl":700},{"code":"APG240115004","name":"Nguyễn Long Nhật","al":2662,"cl":88},{"code":"APG230323005","name":"Võ Minh Kim","al":473,"cl":6},{"code":"APG240202002","name":"Nguyễn Châu Tuấn","al":3773,"cl":1664},{"code":"APG240205002","name":"Huỳnh Quốc Khánh","al":2599,"cl":74},{"code":"APG240226001","name":"Lê Văn Hải","al":5412,"cl":10730},{"code":"APG240130001","name":"Nguyễn Văn Bá","al":123,"cl":265},{"code":"APG240130002","name":"Trần Văn Phúc","al":123,"cl":16},{"code":"APG240319002","name":"Nguyễn Thị Minh Nhi","al":2404,"cl":228},{"code":"APG240304003","name":"Lê An Lộc","al":1309,"cl":249},{"code":"APG240319004","name":"Thiều Quốc Quân","al":5017,"cl":990},{"code":"APG240312004","name":"Lê Trầm Tươi","al":4165,"cl":285},{"code":"APG240401004","name":"Nguyễn Thanh Trí","al":4197,"cl":15067},{"code":"APG240408003","name":"Hồ Thị Kim Chi","al":2782,"cl":37},{"code":"APG240408004","name":"Trần Thị Hồng Phương","al":2192,"cl":1087},{"code":"APG240410004","name":"Nguyễn Tuấn Vũ","al":4192,"cl":10185},{"code":"APG240425002","name":"Nguyễn Anh Thuận","al":3835,"cl":887},{"code":"APG240427003","name":"Trương Hòa Siêu","al":3199,"cl":1140},{"code":"APG240428001","name":"Nguyễn Tuân","al":3904,"cl":408},{"code":"APG231208002","name":"Trương Nữ Hoài Dung","al":27,"cl":0},{"code":"APG240410006","name":"Nguyễn Thành Khang","al":4672,"cl":2675},{"code":"APG240426004","name":"Trần Thị Hồng Loan","al":3456,"cl":66},{"code":"APG240408002","name":"Nguyễn Thị Ngọc Diệm","al":2804,"cl":49},{"code":"APG240405004","name":"Nguyễn Thị Bích Lộc","al":2955,"cl":71},{"code":"APG240405005","name":"Tăng Thị Quyên Chi","al":3217,"cl":125},{"code":"APG240408007","name":"Nguyễn Văn Dũng","al":27,"cl":15},{"code":"APG240408008","name":"Nguyễn Hữu Đức","al":265,"cl":0},{"code":"APG240424002","name":"Nguyễn Thanh Dương","al":2226,"cl":0},{"code":"APG240426006","name":"Nguyễn Thị Thanh Trúc","al":2016,"cl":17},{"code":"APG240426007","name":"Phạm Thị Ngọc Phấn","al":2976,"cl":0},{"code":"APG240426010","name":"Đặng Thị Cúc","al":2496,"cl":47},{"code":"APG240426005","name":"Ngô Quốc Đạt","al":1536,"cl":120},{"code":"APG240410007","name":"Nguyễn Thị Thu Lương","al":3712,"cl":144},{"code":"APG1240419001","name":"Nguyễn Trọng Tình","al":686,"cl":333},{"code":"APG240428003","name":"Thạch Ngọc Tình","al":964,"cl":338},{"code":"APG240422002","name":"Nguyễn Thị Cẩm Giang","al":4000,"cl":564},{"code":"APG240506005","name":"Lê Nguyễn Nguyệt Hà","al":1130,"cl":333},{"code":"APG1240510002","name":"Nguyễn Quốc Việt","al":821,"cl":130},{"code":"APG0240514001","name":"Huỳnh Thị Bích Nhi","al":4119,"cl":5970},{"code":"APG1240510003","name":"Nguyễn Văn Huy","al":2639,"cl":0},{"code":"APG1240510004","name":"Huỳnh Phúc An","al":2071,"cl":19},{"code":"APG1240510005","name":"Võ Phúc Hân","al":3221,"cl":8},{"code":"APG1240527001","name":"Phạm Nguyễn Đình Lân","al":1996,"cl":1080},{"code":"APG1240510006","name":"Trương Thanh Tùng","al":4168,"cl":480},{"code":"APG0240520002","name":"Nguyễn Thị Thủy","al":1893,"cl":0},{"code":"APG0240515008","name":"Trần Thị Thu Diễm","al":391,"cl":3},{"code":"APG1240520003","name":"Huỳnh Quốc Hiệp","al":2106,"cl":131},{"code":"APG1240520004","name":"Trần Bảo Duy","al":3546,"cl":457},{"code":"APG1240527005","name":"Nguyễn Thương Hoài Thanh","al":1037,"cl":74},{"code":"APG240319003","name":"Lê Châu Đại","al":1077,"cl":0},{"code":"APG1240515010","name":"Trần Thanh Vinh","al":1524,"cl":129},{"code":"APG1240607001","name":"Nguyễn Huỳnh Minh Kha","al":1718,"cl":722},{"code":"APG0240617001","name":"Lê Thị Kim Thoa","al":231,"cl":141},{"code":"APG1240603023","name":"Phan Ngọc Trực","al":674,"cl":1},{"code":"APG1240617002","name":"Khê Thành Nhiên","al":1680,"cl":224},{"code":"APG1240617003","name":"Nguyễn Thiên Văn","al":1575,"cl":74},{"code":"APG1240622001","name":"Phạm Thắng","al":1540,"cl":10},{"code":"APG0240603024","name":"Nguyễn Thị Lộc","al":3344,"cl":0},{"code":"APG0240603025","name":"Đỗ Thị Yến Thi","al":3324,"cl":2400},{"code":"APG1240603026","name":"Nguyễn Quốc Khiêm","al":1770,"cl":0},{"code":"APG1240614001","name":"Thái Kim Phương","al":288,"cl":9},{"code":"APG0240617006","name":"Lê Thị Kiều Mỹ","al":2160,"cl":2880},{"code":"APG0240603028","name":"Đặng Thị Thùy Trang","al":1904,"cl":79},{"code":"APG0240603029","name":"Nguyễn Thị Thanh Trúc","al":942,"cl":0},{"code":"APG0240617004","name":"Tạ Hoài Bảo Vi","al":720,"cl":40},{"code":"APG0240603030","name":"Nguyễn Thị Kiều Loan","al":445,"cl":131},{"code":"APG0240603031","name":"Nguyễn Ngọc Quế Anh","al":2384,"cl":370},{"code":"APG1240603032","name":"Phạm Anh Tin","al":3344,"cl":960},{"code":"APG1240610007","name":"Nguyễn Văn Quyền","al":2117,"cl":144},{"code":"APG1240610008","name":"Nguyễn Hữu Nghị","al":1727,"cl":7},{"code":"APG1240617005","name":"Huỳnh Hồng Phước","al":2749,"cl":171},{"code":"APG1240712002","name":"Nguyễn Lê Minh Hiếu","al":1512,"cl":1254},{"code":"APG0240715014","name":"Nguyễn Thị Hoa Sim","al":1558,"cl":101},{"code":"APG0240719001","name":"Nguyễn Thị Hồng Nhung","al":0,"cl":0},{"code":"APG2240722002","name":"Lưu Thị Diễm My","al":2502,"cl":2579},{"code":"APG1240715013","name":"Đỗ Thành Hưng","al":2068,"cl":211},{"code":"APG1240701005","name":"Nguyễn Đức Long","al":1127,"cl":0},{"code":"APG2240701017","name":"Trần Đức Huy","al":1920,"cl":106},{"code":"APG1240712004","name":"Phạm Quốc Thanh Liêm","al":884,"cl":219},{"code":"APG1240715011","name":"Trần Văn Minh Vy","al":180,"cl":61},{"code":"APG1240718004","name":"Lê Văn Đan","al":173,"cl":471},{"code":"APG1240718005","name":"Nguyễn Hồng Nghĩa","al":3053,"cl":6703},{"code":"APG0240718007","name":"Hồ Quận Chúa","al":173,"cl":105},{"code":"APG2240722003","name":"Nguyễn Đức Phương","al":197,"cl":155},{"code":"APG2240701010","name":"Đậu Văn Thượng","al":2606,"cl":0},{"code":"APG2240701019","name":"Nguyễn Ngọc Thuận","al":122,"cl":27},{"code":"APG2240701016","name":"Lê Thị Trúc Giang","al":2400,"cl":429},{"code":"APG2240701009","name":"Nguyễn Duy Hậu","al":2880,"cl":19},{"code":"APG2240701013","name":"Trần Thị Qúy","al":1124,"cl":110},{"code":"APG0240710001","name":"Đinh Phong Hạnh","al":2261,"cl":106},{"code":"APG0240712005","name":"Trương Thị Mỹ Hoa","al":2710,"cl":1440},{"code":"APG1240719002","name":"Trần Công Anh","al":323,"cl":80},{"code":"APG2240701011","name":"Nguyễn Thanh Long","al":2880,"cl":6079},{"code":"APG1240712007","name":"Nguyễn Thanh Hoài","al":1856,"cl":0},{"code":"APG2240701007","name":"Nguyễn Hoài Vũ","al":67,"cl":14},{"code":"APG2240701018","name":"Nguyễn Xuân Vinh","al":720,"cl":188},{"code":"APG1240718008","name":"Đặng Thành Vũ","al":13,"cl":2},{"code":"APG1240718009","name":"Huỳnh Phát","al":3053,"cl":787},{"code":"APG1240718011","name":"Nguyễn Công Luận","al":3053,"cl":247},{"code":"APG1240718012","name":"Nguyễn Xuân Thanh","al":2105,"cl":70},{"code":"APG0240801009","name":"Trần Thị Kim Xuyến","al":959,"cl":0},{"code":"APG1240808001","name":"Võ Đức Lâm","al":1332,"cl":0},{"code":"APG1240826008","name":"Nguyễn Hồng Thái Huy","al":2348,"cl":1794},{"code":"APG1240812001","name":"Nguyễn Thị Thanh Hải","al":2601,"cl":540},{"code":"APG1240801008","name":"Phạm Ngọc Thịnh","al":1360,"cl":130},{"code":"APG1240814004","name":"Lê Khắc Hoài","al":2199,"cl":986},{"code":"APG1240814003","name":"Lê Xuân Hà","al":2199,"cl":2543},{"code":"APG0240801015","name":"Nguyễn Xuân Hà","al":1920,"cl":25},{"code":"APG1240801015","name":"Bùi Thanh Tường","al":960,"cl":183},{"code":"APG1240805002","name":"Đào Thanh Tý","al":1070,"cl":0},{"code":"APG0240801004","name":"Nông Duyên Trinh","al":1764,"cl":1854},{"code":"APG0240801011","name":"Dương Thị Thùy Dung","al":2400,"cl":2400},{"code":"APG0240801010","name":"Nguyễn Ngọc Bích Ngân","al":1886,"cl":1440},{"code":"APG0240801005","name":"Đặng Mai Như Ý","al":876,"cl":946},{"code":"APG230317011","name":"Trần Thị Ngọc Nữ","al":2832,"cl":53},{"code":"APG1240712009","name":"Nguyễn Thanh Hoài","al":0,"cl":0},{"code":"APG1241113001","name":"Phan Cao Trung","al":0,"cl":0},{"code":"APG1241118002","name":"Nguyễn Hữu Đức","al":0,"cl":0},{"code":"APG0241108001","name":"An Linh Đan","al":0,"cl":0},{"code":"APG0241118003","name":"Đào Thị Yến Phi","al":0,"cl":0},{"code":"APG0241104007","name":"Trương Như Ngọc","al":0,"cl":0},{"code":"APG1241104007","name":"Lê Bá Thịnh","al":0,"cl":0},{"code":"APG1241209001","name":"Dương Quốc Ngọc","al":0,"cl":0},{"code":"APG1241205002","name":"Nguyễn Văn Du","al":0,"cl":0},{"code":"APG1241202001","name":"Nguyễn Đăng Trung Hiếu","al":0,"cl":0}]